scopus_mcp/__init__.py
scopus_mcp/cache.py
scopus_mcp/client.py
scopus_mcp/config.py
scopus_mcp/server.py
scopus_mcp/utils.py
scopus_mcp-0.1.8.dist-info/METADATA
scopus_mcp-0.1.8.dist-info/WHEEL
scopus_mcp-0.1.8.dist-info/entry_points.txt
scopus_mcp-0.1.8.dist-info/licenses/LICENSE
scopus_mcp-0.1.8.dist-info/RECORD
