Metadata-Version: 2.4
Name: scopus-mcp
Version: 0.1.8
Summary: A Model Context Protocol server for the Elsevier Scopus API
Project-URL: Homepage, https://github.com/qwe4559999/scopus-mcp
Project-URL: Documentation, https://github.com/qwe4559999/scopus-mcp/blob/main/README.md
Project-URL: Repository, https://github.com/qwe4559999/scopus-mcp
Project-URL: Issues, https://github.com/qwe4559999/scopus-mcp/issues
Author: thinktraveller
Author-email: qwe4559999 <heyrhao@126.com>
License-File: LICENSE
Requires-Python: >=3.10
Requires-Dist: httpx>=0.27.0
Requires-Dist: mcp>=0.1.0
Requires-Dist: python-dotenv>=1.0.0
Provides-Extra: dev
Requires-Dist: pytest-mock>=3.11.1; extra == 'dev'
Requires-Dist: pytest>=7.4.0; extra == 'dev'
